README.rst
setup.cfg
setup.py
djangosecure/__init__.py
djangosecure/cryptolib.py
djangosecure/files_dirs_lib.py
djangosecure/tests.py
djangosecure.egg-info/PKG-INFO
djangosecure.egg-info/SOURCES.txt
djangosecure.egg-info/dependency_links.txt
djangosecure.egg-info/requires.txt
djangosecure.egg-info/top_level.txt