Metadata-Version: 1.1
Name: djangosecure
Version: 0.0.3
Summary: Secure your django sensible settings
Home-page: https://github.com/rafahsolis/djangosecure
Author: Rafael Herrero Solis
Author-email: rafael@herrerosolis.com
License: Apache License, Version 2.0
Download-URL: https://github.com/rafahsolis/djangosecure/tarball/v0.0.3
Keywords: django,secure,settings
Platform: UNKNOWN
Classifier: Development Status :: 3 - Alpha
Classifier: License :: OSI Approved :: Apache Software License
Classifier: Programming Language :: Python
Classifier: Programming Language :: Python :: 2.7
Classifier: Programming Language :: Python :: 3.5
